setup.py
chiasma/__init__.py
chiasma/command.py
chiasma/mod_pane.py
chiasma/open_pane.py
chiasma/pane.py
chiasma/render.py
chiasma/session.py
chiasma/tmux.py
chiasma/view_path.py
chiasma.egg-info/PKG-INFO
chiasma.egg-info/SOURCES.txt
chiasma.egg-info/dependency_links.txt
chiasma.egg-info/requires.txt
chiasma.egg-info/top_level.txt
chiasma/commands/__init__.py
chiasma/commands/pane.py
chiasma/commands/server.py
chiasma/commands/session.py
chiasma/commands/window.py
chiasma/data/__init__.py
chiasma/data/pane.py
chiasma/data/session.py
chiasma/data/tmux.py
chiasma/data/view_tree.py
chiasma/data/window.py
chiasma/io/__init__.py
chiasma/io/compute.py
chiasma/io/data.py
chiasma/io/execute.py
chiasma/io/state.py
chiasma/io/tc.py
chiasma/io/trace.py
chiasma/io/util.py
chiasma/native/__init__.py
chiasma/test/__init__.py
chiasma/test/terminal.py
chiasma/test/tmux_spec.py
chiasma/ui/__init__.py
chiasma/ui/simple.py
chiasma/ui/state.py
chiasma/ui/view.py
chiasma/ui/view_geometry.py
chiasma/util/__init__.py
chiasma/util/id.py
chiasma/util/pid.py
chiasma/window/__init__.py
chiasma/window/main.py
chiasma/window/measure.py
chiasma/window/principal.py