Metadata-Version: 1.0
Name: chiasma
Version: 0.1.0a26
Summary: tmux layout renderer
Home-page: https://github.com/tek/chiasma
Author: Torsten Schmits
Author-email: torstenschmits@gmail.com
License: MIT
Platform: UNKNOWN
